Workbook

Sheet README
A1: xirr-rs golden-value corpus
A3: HOW TO REGENERATE GOLDEN VALUES FROM A REAL SPREADSHEET ENGINE
A4: 1. Open this workbook in Excel, Google Sheets, or LibreOffice Calc.
A5: 2. Let it recalculate. The 'results' sheet column D computes XIRR() natively.
A6: 3. Copy 'results' columns A and D into golden_<engine>.csv (case_id,expected).
A7: 4. A cell showing the numeric-error marker means the engine could not solve it; record NUM.
A9: Column D formula: =IFERROR(XIRR(amount_range, date_range), "NUM")
A10: Guess is left at the engine default of 10%, matching production callers.
A12: Cash flows live on the 'flows' sheet in long format, one row per payment,
A13: grouped by case_id and already in the exact input order the library receives.
A14: Input order is significant: XIRR uses the FIRST row of each block as the
A15: reference date, not the earliest date.
... A18: Cases: 89

Sheet flows
A1: case_id | B1: date | C1: amount
A2: conventional/textbook-3flow | B2: 43831 | C2: -1000
A3: conventional/textbook-3flow | B3: 44197 | C3: 750
A4: conventional/textbook-3flow | B4: 44562 | C4: 500
A5: conventional/one-year-30pct | B5: 43831 | C5: -100
A6: conventional/one-year-30pct | B6: 44197 | C6: 130
A7: conventional/monthly-12 | B7: 44197 | C7: -100
A8: conventional/monthly-12 | B8: 44228 | C8: 20
A9: conventional/monthly-12 | B9: 44256 | C9: 20
A10: conventional/monthly-12 | B10: 44287 | C10: 20
A11: conventional/monthly-12 | B11: 44317 | C11: 20
A12: conventional/monthly-12 | B12: 44348 | C12: 20
A13: conventional/monthly-12 | B13: 44378 | C13: 20
... A481: fuzz/058 | B481: 43558 | C481: 3356

Sheet results
A1: case_id | B1: n_flows | C1: sign_changes | D1: xirr | E1: xnpv_at_xirr
A2: conventional/textbook-3flow | B2: 3 | C2: 1 | D2: =IFERROR(XIRR(flows!$C$2:$C$4,flows!$B$2:$B$4),"NUM") -> 0.17500926 | E2: =IF(ISNUMBER(D2),IFERROR(XNPV(D2,flows!$C$2:$C$4,flows!$B$2:$B$4),"ERR"),"") -> 0
A3: conventional/one-year-30pct | B3: 2 | C3: 1 | D3: =IFERROR(XIRR(flows!$C$5:$C$6,flows!$B$5:$B$6),"NUM") -> 0.29906844 | E3: =IF(ISNUMBER(D3),IFERROR(XNPV(D3,flows!$C$5:$C$6,flows!$B$5:$B$6),"ERR"),"") -> 1.4210855e-14
A4: conventional/monthly-12 | B4: 12 | C4: 1 | D4: =IFERROR(XIRR(flows!$C$7:$C$18,flows!$B$7:$B$18),"NUM") -> 5.0962355 | E4: =IF(ISNUMBER(D4),IFERROR(XNPV(D4,flows!$C$7:$C$18,flows!$B$7:$B$18),"ERR"),"") -> -8.8817842e-16
A5: conventional/quarterly-drawdown | B5: 6 | C5: 1 | D5: =IFERROR(XIRR(flows!$C$19:$C$24,flows!$B$19:$B$24),"NUM") -> 0.085316639 | E5: =IF(ISNUMBER(D5),IFERROR(XNPV(D5,flows!$C$19:$C$24,flows!$B$19:$B$24),"ERR"),"") -> -3.6379788e-12
A6: conventional/leap-year-span | B6: 2 | C6: 1 | D6: =IFERROR(XIRR(flows!$C$25:$C$26,flows!$B$25:$B$26),"NUM") -> 0.14956094 | E6: =IF(ISNUMBER(D6),IFERROR(XNPV(D6,flows!$C$25:$C$26,flows!$B$25:$B$26),"ERR"),"") -> 1.1368684e-13
A7: horizon/30y-50x | B7: 2 | C7: 1 | D7: =IFERROR(XIRR(flows!$C$27:$C$28,flows!$B$27:$B$28),"NUM") -> 0.13918997 | E7: =IF(ISNUMBER(D7),IFERROR(XNPV(D7,flows!$C$27:$C$28,flows!$B$27:$B$28),"ERR"),"") -> 2.0463631e-12
A8: horizon/50y-50x | B8: 2 | C8: 1 | D8: =IFERROR(XIRR(flows!$C$29:$C$30,flows!$B$29:$B$30),"NUM") -> 0.081322433 | E8: =IF(ISNUMBER(D8),IFERROR(XNPV(D8,flows!$C$29:$C$30,flows!$B$29:$B$30),"ERR"),"") -> 3.4106051e-13
A9: horizon/5-day-10pct | B9: 2 | C9: 1 | D9: =IFERROR(XIRR(flows!$C$31:$C$32,flows!$B$31:$B$32),"NUM") -> 1050.1532 | E9: =IF(ISNUMBER(D9),IFERROR(XNPV(D9,flows!$C$31:$C$32,flows!$B$31:$B$32),"ERR"),"") -> 1.1368684e-13
A10: horizon/1-day | B10: 2 | C10: 1 | D10: =IFERROR(XIRR(flows!$C$33:$C$34,flows!$B$33:$B$34),"NUM") -> 0.44025131 | E10: =IF(ISNUMBER(D10),IFERROR(XNPV(D10,flows!$C$33:$C$34,flows!$B$33:$B$34),"ERR"),"") -> 1.1368684e-13
A11: horizon/tiny-basis-10y | B11: 3 | C11: 1 | D11: =IFERROR(XIRR(flows!$C$35:$C$37,flows!$B$35:$B$37),"NUM") -> 2.7111359 | E11: =IF(ISNUMBER(D11),IFERROR(XNPV(D11,flows!$C$35:$C$37,flows!$B$35:$B$37),"ERR"),"") -> -2.220446e-16
A12: rate/near-zero-positive | B12: 2 | C12: 1 | D12: =IFERROR(XIRR(flows!$C$38:$C$39,flows!$B$38:$B$39),"NUM") -> 9.9726776e-08 | E12: =IF(ISNUMBER(D12),IFERROR(XNPV(D12,flows!$C$38:$C$39,flows!$B$38:$B$39),"ERR"),"") -> -1.1368684e-13
A13: rate/exact-zero | B13: 2 | C13: 1 | D13: =IFERROR(XIRR(flows!$C$40:$C$41,flows!$B$40:$B$41),"NUM") -> 2.1696732e-17 | E13: =IF(ISNUMBER(D13),IFERROR(XNPV(D13,flows!$C$40:$C$41,flows!$B$40:$B$41),"ERR"),"") -> 0
A14: rate/near-zero-negative | B14: 2 | C14: 1 | D14: =IFERROR(XIRR(flows!$C$42:$C$43,flows!$B$42:$B$43),"NUM") -> -9.9726776e-08 | E14: =IF(ISNUMBER(D14),IFERROR(XNPV(D14,flows!$C$42:$C$43,flows!$B$42:$B$43),"ERR"),"") -> 0
A15: rate/near-total-loss | B15: 2 | C15: 1 | D15: =IFERROR(XIRR(flows!$C$44:$C$45,flows!$B$44:$B$45),"NUM") -> NUM | E15: =IF(ISNUMBER(D15),IFERROR(XNPV(D15,flows!$C$44:$C$45,flows!$B$44:$B$45),"ERR"),"")
A16: rate/deep-negative | B16: 3 | C16: 1 | D16: =IFERROR(XIRR(flows!$C$46:$C$48,flows!$B$46:$B$48),"NUM") -> -0.81442744 | E16: =IF(ISNUMBER(D16),IFERROR(XNPV(D16,flows!$C$46:$C$48,flows!$B$46:$B$48),"ERR"),"") -> 0
A17: multiroot/classic-100-230-132 | B17: 3 | C17: 2 | D17: =IFERROR(XIRR(flows!$C$49:$C$51,flows!$B$49:$B$51),"NUM") -> 0.10339793 | E17: =IF(ISNUMBER(D17),IFERROR(XNPV(D17,flows!$C$49:$C$51,flows!$B$49:$B$51),"ERR"),"") -> 2.8421709e-14
A18: multiroot/sign-reversal-monthly | B18: 3 | C18: 2 | D18: =IFERROR(XIRR(flows!$C$52:$C$54,flows!$B$52:$B$54),"NUM") -> -0.70240549 | E18: =IF(ISNUMBER(D18),IFERROR(XNPV(D18,flows!$C$52:$C$54,flows!$B$52:$B$54),"ERR"),"") -> 0
A19: multiroot/three-roots | B19: 4 | C19: 3 | D19: =IFERROR(XIRR(flows!$C$55:$C$58,flows!$B$55:$B$58),"NUM") -> -0.57188595 | E19: =IF(ISNUMBER(D19),IFERROR(XNPV(D19,flows!$C$55:$C$58,flows!$B$55:$B$58),"ERR"),"") -> -1.8189894e-12
A20: multiroot/pe-recall | B20: 4 | C20: 3 | D20: =IFERROR(XIRR(flows!$C$59:$C$62,flows!$B$59:$B$62),"NUM") -> 2.4825548 | E20: =IF(ISNUMBER(D20),IFERROR(XNPV(D20,flows!$C$59:$C$62,flows!$B$59:$B$62),"ERR"),"") -> -1.4210855e-14
A21: multiroot/five-flips | B21: 5 | C21: 4 | D21: =IFERROR(XIRR(flows!$C$63:$C$67,flows!$B$63:$B$67),"NUM") -> -0.96428712 | E21: =IF(ISNUMBER(D21),IFERROR(XNPV(D21,flows!$C$63:$C$67,flows!$B$63:$B$67),"ERR"),"") -> 0
A22: multiroot/capital-call-mid | B22: 4 | C22: 3 | D22: =IFERROR(XIRR(flows!$C$68:$C$71,flows!$B$68:$B$71),"NUM") -> 0.13008746 | E22: =IF(ISNUMBER(D22),IFERROR(XNPV(D22,flows!$C$68:$C$71,flows!$B$68:$B$71),"ERR"),"") -> 2.2737368e-13
A23: scale/1e0-conventional | B23: 3 | C23: 1 | D23: =IFERROR(XIRR(flows!$C$72:$C$74,flows!$B$72:$B$74),"NUM") -> 0.17500926 | E23: =IF(ISNUMBER(D23),IFERROR(XNPV(D23,flows!$C$72:$C$74,flows!$B$72:$B$74),"ERR"),"") -> 0
A24: scale/1e0-multiroot | B24: 4 | C24: 3 | D24: =IFERROR(XIRR(flows!$C$75:$C$78,flows!$B$75:$B$78),"NUM") -> 2.4646907 | E24: =IF(ISNUMBER(D24),IFERROR(XNPV(D24,flows!$C$75:$C$78,flows!$B$75:$B$78),"ERR"),"") -> -1.9895197e-13
A25: scale/1e3-conventional | B25: 3 | C25: 1 | D25: =IFERROR(XIRR(flows!$C$79:$C$81,flows!$B$79:$B$81),"NUM") -> 0.17500926 | E25: =IF(ISNUMBER(D25),IFERROR(XNPV(D25,flows!$C$79:$C$81,flows!$B$79:$B$81),"ERR"),"") -> -2.3283064e-10
A26: scale/1e3-multiroot | B26: 4 | C26: 3 | D26: =IFERROR(XIRR(flows!$C$82:$C$85,flows!$B$82:$B$85),"NUM") -> 2.4646907 | E26: =IF(ISNUMBER(D26),IFERROR(XNPV(D26,flows!$C$82:$C$85,flows!$B$82:$B$85),"ERR"),"") -> 2.0372681e-10
A27: scale/1e6-conventional | B27: 3 | C27: 1 | D27: =IFERROR(XIRR(flows!$C$86:$C$88,flows!$B$86:$B$88),"NUM") -> 0.17500926 | E27: =IF(ISNUMBER(D27),IFERROR(XNPV(D27,flows!$C$86:$C$88,flows!$B$86:$B$88),"ERR"),"") -> 0
A28: scale/1e6-multiroot | B28: 4 | C28: 3 | D28: =IFERROR(XIRR(flows!$C$89:$C$92,flows!$B$89:$B$92),"NUM") -> 2.4646907 | E28: =IF(ISNUMBER(D28),IFERROR(XNPV(D28,flows!$C$89:$C$92,flows!$B$89:$B$92),"ERR"),"") -> 4.4703484e-08
A29: scale/1e9-conventional | B29: 3 | C29: 1 | D29: =IFERROR(XIRR(flows!$C$93:$C$95,flows!$B$93:$B$95),"NUM") -> 0.17500926 | E29: =IF(ISNUMBER(D29),IFERROR(XNPV(D29,flows!$C$93:$C$95,flows!$B$93:$B$95),"ERR"),"") -> -6.1035156e-05
A30: scale/1e9-multiroot | B30: 4 | C30: 3 | D30: =IFERROR(XIRR(flows!$C$96:$C$99,flows!$B$96:$B$99),"NUM") -> 2.4646907 | E30: =IF(ISNUMBER(D30),IFERROR(XNPV(D30,flows!$C$96:$C$99,flows!$B$96:$B$99),"ERR"),"") -> 0.00016021729
A31: scale/1e12-conventional | B31: 3 | C31: 1 | D31: =IFERROR(XIRR(flows!$C$100:$C$102,flows!$B$100:$B$102),"NUM") -> 0.17500926 | E31: =IF(ISNUMBER(D31),IFERROR(XNPV(D31,flows!$C$100:$C$102,flows!$B$100:$B$102),"ERR"),"") -> 0.25
A32: scale/1e12-multiroot | B32: 4 | C32: 3 | D32: =IFERROR(XIRR(flows!$C$103:$C$106,flows!$B$103:$B$106),"NUM") -> 2.4646907 | E32: =IF(ISNUMBER(D32),IFERROR(XNPV(D32,flows!$C$103:$C$106,flows!$B$103:$B$106),"ERR"),"") -> -0.0390625
A33: scale/sub-cent | B33: 2 | C33: 1 | D33: =IFERROR(XIRR(flows!$C$107:$C$108,flows!$B$107:$B$108),"NUM") -> 0.24923813 | E33: =IF(ISNUMBER(D33),IFERROR(XNPV(D33,flows!$C$107:$C$108,flows!$B$107:$B$108),"ERR"),"") -> 0
A34: edge/zero-amounts-interleaved | B34: 4 | C34: 0 | D34: =IFERROR(XIRR(flows!$C$109:$C$112,flows!$B$109:$B$112),"NUM") -> 0.13997083 | E34: =IF(ISNUMBER(D34),IFERROR(XNPV(D34,flows!$C$109:$C$112,flows!$B$109:$B$112),"ERR"),"") -> 0
A35: edge/duplicate-dates | B35: 3 | C35: 1 | D35: =IFERROR(XIRR(flows!$C$113:$C$115,flows!$B$113:$B$115),"NUM") -> 0.13997083 | E35: =IF(ISNUMBER(D35),IFERROR(XNPV(D35,flows!$C$113:$C$115,flows!$B$113:$B$115),"ERR"),"") -> 0
A36: edge/many-flows-60 | B36: 60 | C36: 1 | D36: =IFERROR(XIRR(flows!$C$116:$C$175,flows!$B$116:$B$175),"NUM") -> 0.012937937 | E36: =IF(ISNUMBER(D36),IFERROR(XNPV(D36,flows!$C$116:$C$175,flows!$B$116:$B$175),"ERR"),"") -> 1.5347723e-12
A37: edge/trailing-zero | B37: 3 | C37: 1 | D37: =IFERROR(XIRR(flows!$C$176:$C$178,flows!$B$176:$B$178),"NUM") -> 0.19940237 | E37: =IF(ISNUMBER(D37),IFERROR(XNPV(D37,flows!$C$176:$C$178,flows!$B$176:$B$178),"ERR"),"") -> 0
A38: nosolution/lease-tail | B38: 3 | C38: 1 | D38: =IFERROR(XIRR(flows!$C$179:$C$181,flows!$B$179:$B$181),"NUM") -> NUM | E38: =IF(ISNUMBER(D38),IFERROR(XNPV(D38,flows!$C$179:$C$181,flows!$B$179:$B$181),"ERR"),"")
A39: nosolution/all-tiny-outflow | B39: 3 | C39: 1 | D39: =IFERROR(XIRR(flows!$C$182:$C$184,flows!$B$182:$B$184),"NUM") -> 9.3313688e+10 | E39: =IF(ISNUMBER(D39),IFERROR(XNPV(D39,flows!$C$182:$C$184,flows!$B$182:$B$184),"ERR"),"") -> 1.9079841e-17
A40: fuzz/000 | B40: 4 | C40: 2 | D40: =IFERROR(XIRR(flows!$C$185:$C$188,flows!$B$185:$B$188),"NUM") -> NUM | E40: =IF(ISNUMBER(D40),IFERROR(XNPV(D40,flows!$C$185:$C$188,flows!$B$185:$B$188),"ERR"),"")
A41: fuzz/001 | B41: 8 | C41: 3 | D41: =IFERROR(XIRR(flows!$C$189:$C$196,flows!$B$189:$B$196),"NUM") -> 0.26301825 | E41: =IF(ISNUMBER(D41),IFERROR(XNPV(D41,flows!$C$189:$C$196,flows!$B$189:$B$196),"ERR"),"") -> 2.2737368e-13
A42: fuzz/002 | B42: 3 | C42: 1 | D42: =IFERROR(XIRR(flows!$C$197:$C$199,flows!$B$197:$B$199),"NUM") -> -0.42426632 | E42: =IF(ISNUMBER(D42),IFERROR(XNPV(D42,flows!$C$197:$C$199,flows!$B$197:$B$199),"ERR"),"") -> 0
A43: fuzz/003 | B43: 3 | C43: 1 | D43: =IFERROR(XIRR(flows!$C$200:$C$202,flows!$B$200:$B$202),"NUM") -> -0.83031645 | E43: =IF(ISNUMBER(D43),IFERROR(XNPV(D43,flows!$C$200:$C$202,flows!$B$200:$B$202),"ERR"),"") -> 3.6379788e-12
A44: fuzz/004 | B44: 7 | C44: 3 | D44: =IFERROR(XIRR(flows!$C$203:$C$209,flows!$B$203:$B$209),"NUM") -> -0.15207047 | E44: =IF(ISNUMBER(D44),IFERROR(XNPV(D44,flows!$C$203:$C$209,flows!$B$203:$B$209),"ERR"),"") -> 0
A45: fuzz/005 | B45: 5 | C45: 1 | D45: =IFERROR(XIRR(flows!$C$210:$C$214,flows!$B$210:$B$214),"NUM") -> 0.2157574 | E45: =IF(ISNUMBER(D45),IFERROR(XNPV(D45,flows!$C$210:$C$214,flows!$B$210:$B$214),"ERR"),"") -> -4.5474735e-13
A46: fuzz/006 | B46: 6 | C46: 2 | D46: =IFERROR(XIRR(flows!$C$215:$C$220,flows!$B$215:$B$220),"NUM") -> NUM | E46: =IF(ISNUMBER(D46),IFERROR(XNPV(D46,flows!$C$215:$C$220,flows!$B$215:$B$220),"ERR"),"")
A47: fuzz/008 | B47: 7 | C47: 2 | D47: =IFERROR(XIRR(flows!$C$221:$C$227,flows!$B$221:$B$227),"NUM") -> NUM | E47: =IF(ISNUMBER(D47),IFERROR(XNPV(D47,flows!$C$221:$C$227,flows!$B$221:$B$227),"ERR"),"")
A48: fuzz/010 | B48: 7 | C48: 3 | D48: =IFERROR(XIRR(flows!$C$228:$C$234,flows!$B$228:$B$234),"NUM") -> 0.61547241 | E48: =IF(ISNUMBER(D48),IFERROR(XNPV(D48,flows!$C$228:$C$234,flows!$B$228:$B$234),"ERR"),"") -> -1.1368684e-12
A49: fuzz/011 | B49: 4 | C49: 1 | D49: =IFERROR(XIRR(flows!$C$235:$C$238,flows!$B$235:$B$238),"NUM") -> 2.0340196 | E49: =IF(ISNUMBER(D49),IFERROR(XNPV(D49,flows!$C$235:$C$238,flows!$B$235:$B$238),"ERR"),"") -> 1.9895197e-13
A50: fuzz/012 | B50: 7 | C50: 3 | D50: =IFERROR(XIRR(flows!$C$239:$C$245,flows!$B$239:$B$245),"NUM") -> 0.82455251 | E50: =IF(ISNUMBER(D50),IFERROR(XNPV(D50,flows!$C$239:$C$245,flows!$B$239:$B$245),"ERR"),"") -> -2.2737368e-13
A51: fuzz/013 | B51: 8 | C51: 3 | D51: =IFERROR(XIRR(flows!$C$246:$C$253,flows!$B$246:$B$253),"NUM") -> -0.23628423 | E51: =IF(ISNUMBER(D51),IFERROR(XNPV(D51,flows!$C$246:$C$253,flows!$B$246:$B$253),"ERR"),"") -> 1.8189894e-12
A52: fuzz/014 | B52: 7 | C52: 4 | D52: =IFERROR(XIRR(flows!$C$254:$C$260,flows!$B$254:$B$260),"NUM") -> 9.7053888 | E52: =IF(ISNUMBER(D52),IFERROR(XNPV(D52,flows!$C$254:$C$260,flows!$B$254:$B$260),"ERR"),"") -> -4.576374e-14
A53: fuzz/015 | B53: 4 | C53: 2 | D53: =IFERROR(XIRR(flows!$C$261:$C$264,flows!$B$261:$B$264),"NUM") -> -0.11324436 | E53: =IF(ISNUMBER(D53),IFERROR(XNPV(D53,flows!$C$261:$C$264,flows!$B$261:$B$264),"ERR"),"") -> -5.6843419e-13
A54: fuzz/016 | B54: 7 | C54: 3 | D54: =IFERROR(XIRR(flows!$C$265:$C$271,flows!$B$265:$B$271),"NUM") -> 0.072153321 | E54: =IF(ISNUMBER(D54),IFERROR(XNPV(D54,flows!$C$265:$C$271,flows!$B$265:$B$271),"ERR"),"") -> 4.5474735e-13
A55: fuzz/017 | B55: 8 | C55: 4 | D55: =IFERROR(XIRR(flows!$C$272:$C$279,flows!$B$272:$B$279),"NUM") -> 0.12622503 | E55: =IF(ISNUMBER(D55),IFERROR(XNPV(D55,flows!$C$272:$C$279,flows!$B$272:$B$279),"ERR"),"") -> -2.4158453e-13
A56: fuzz/018 | B56: 3 | C56: 2 | D56: =IFERROR(XIRR(flows!$C$280:$C$282,flows!$B$280:$B$282),"NUM") -> 2.1089147 | E56: =IF(ISNUMBER(D56),IFERROR(XNPV(D56,flows!$C$280:$C$282,flows!$B$280:$B$282),"ERR"),"") -> -1.7053026e-13
A57: fuzz/019 | B57: 6 | C57: 2 | D57: =IFERROR(XIRR(flows!$C$283:$C$288,flows!$B$283:$B$288),"NUM") -> NUM | E57: =IF(ISNUMBER(D57),IFERROR(XNPV(D57,flows!$C$283:$C$288,flows!$B$283:$B$288),"ERR"),"")
A58: fuzz/021 | B58: 5 | C58: 4 | D58: =IFERROR(XIRR(flows!$C$289:$C$293,flows!$B$289:$B$293),"NUM") -> -0.84510461 | E58: =IF(ISNUMBER(D58),IFERROR(XNPV(D58,flows!$C$289:$C$293,flows!$B$289:$B$293),"ERR"),"") -> 0
A59: fuzz/024 | B59: 5 | C59: 1 | D59: =IFERROR(XIRR(flows!$C$294:$C$298,flows!$B$294:$B$298),"NUM") -> -0.53988925 | E59: =IF(ISNUMBER(D59),IFERROR(XNPV(D59,flows!$C$294:$C$298,flows!$B$294:$B$298),"ERR"),"") -> -7.2759576e-12
A60: fuzz/025 | B60: 8 | C60: 3 | D60: =IFERROR(XIRR(flows!$C$299:$C$306,flows!$B$299:$B$306),"NUM") -> -0.15416822 | E60: =IF(ISNUMBER(D60),IFERROR(XNPV(D60,flows!$C$299:$C$306,flows!$B$299:$B$306),"ERR"),"") -> 9.094947e-13
A61: fuzz/026 | B61: 5 | C61: 2 | D61: =IFERROR(XIRR(flows!$C$307:$C$311,flows!$B$307:$B$311),"NUM") -> NUM | E61: =IF(ISNUMBER(D61),IFERROR(XNPV(D61,flows!$C$307:$C$311,flows!$B$307:$B$311),"ERR"),"")
A62: fuzz/027 | B62: 5 | C62: 3 | D62: =IFERROR(XIRR(flows!$C$312:$C$316,flows!$B$312:$B$316),"NUM") -> 0.050099083 | E62: =IF(ISNUMBER(D62),IFERROR(XNPV(D62,flows!$C$312:$C$316,flows!$B$312:$B$316),"ERR"),"") -> -4.5474735e-13
A63: fuzz/028 | B63: 3 | C63: 1 | D63: =IFERROR(XIRR(flows!$C$317:$C$319,flows!$B$317:$B$319),"NUM") -> -0.56471532 | E63: =IF(ISNUMBER(D63),IFERROR(XNPV(D63,flows!$C$317:$C$319,flows!$B$317:$B$319),"ERR"),"") -> 0
A64: fuzz/029 | B64: 4 | C64: 2 | D64: =IFERROR(XIRR(flows!$C$320:$C$323,flows!$B$320:$B$323),"NUM") -> NUM | E64: =IF(ISNUMBER(D64),IFERROR(XNPV(D64,flows!$C$320:$C$323,flows!$B$320:$B$323),"ERR"),"")
A65: fuzz/030 | B65: 6 | C65: 3 | D65: =IFERROR(XIRR(flows!$C$324:$C$329,flows!$B$324:$B$329),"NUM") -> -0.40001108 | E65: =IF(ISNUMBER(D65),IFERROR(XNPV(D65,flows!$C$324:$C$329,flows!$B$324:$B$329),"ERR"),"") -> -1.8189894e-12
A66: fuzz/031 | B66: 5 | C66: 2 | D66: =IFERROR(XIRR(flows!$C$330:$C$334,flows!$B$330:$B$334),"NUM") -> -0.0051859553 | E66: =IF(ISNUMBER(D66),IFERROR(XNPV(D66,flows!$C$330:$C$334,flows!$B$330:$B$334),"ERR"),"") -> -9.094947e-13
A67: fuzz/032 | B67: 4 | C67: 3 | D67: =IFERROR(XIRR(flows!$C$335:$C$338,flows!$B$335:$B$338),"NUM") -> -0.46876957 | E67: =IF(ISNUMBER(D67),IFERROR(XNPV(D67,flows!$C$335:$C$338,flows!$B$335:$B$338),"ERR"),"") -> 1.8189894e-12
A68: fuzz/033 | B68: 6 | C68: 2 | D68: =IFERROR(XIRR(flows!$C$339:$C$344,flows!$B$339:$B$344),"NUM") -> NUM | E68: =IF(ISNUMBER(D68),IFERROR(XNPV(D68,flows!$C$339:$C$344,flows!$B$339:$B$344),"ERR"),"")
A69: fuzz/034 | B69: 7 | C69: 1 | D69: =IFERROR(XIRR(flows!$C$345:$C$351,flows!$B$345:$B$351),"NUM") -> -0.24172285 | E69: =IF(ISNUMBER(D69),IFERROR(XNPV(D69,flows!$C$345:$C$351,flows!$B$345:$B$351),"ERR"),"") -> 3.6379788e-12
A70: fuzz/035 | B70: 3 | C70: 2 | D70: =IFERROR(XIRR(flows!$C$352:$C$354,flows!$B$352:$B$354),"NUM") -> 0.022130312 | E70: =IF(ISNUMBER(D70),IFERROR(XNPV(D70,flows!$C$352:$C$354,flows!$B$352:$B$354),"ERR"),"") -> 0
A71: fuzz/036 | B71: 5 | C71: 2 | D71: =IFERROR(XIRR(flows!$C$355:$C$359,flows!$B$355:$B$359),"NUM") -> NUM | E71: =IF(ISNUMBER(D71),IFERROR(XNPV(D71,flows!$C$355:$C$359,flows!$B$355:$B$359),"ERR"),"")
A72: fuzz/037 | B72: 7 | C72: 2 | D72: =IFERROR(XIRR(flows!$C$360:$C$366,flows!$B$360:$B$366),"NUM") -> -0.1377022 | E72: =IF(ISNUMBER(D72),IFERROR(XNPV(D72,flows!$C$360:$C$366,flows!$B$360:$B$366),"ERR"),"") -> 4.5474735e-13
A73: fuzz/038 | B73: 7 | C73: 3 | D73: =IFERROR(XIRR(flows!$C$367:$C$373,flows!$B$367:$B$373),"NUM") -> -0.70534109 | E73: =IF(ISNUMBER(D73),IFERROR(XNPV(D73,flows!$C$367:$C$373,flows!$B$367:$B$373),"ERR"),"") -> 1.1641532e-10
A74: fuzz/039 | B74: 6 | C74: 3 | D74: =IFERROR(XIRR(flows!$C$374:$C$379,flows!$B$374:$B$379),"NUM") -> -0.99883984 | E74: =IF(ISNUMBER(D74),IFERROR(XNPV(D74,flows!$C$374:$C$379,flows!$B$374:$B$379),"ERR"),"") -> -1.015625
A75: fuzz/040 | B75: 6 | C75: 1 | D75: =IFERROR(XIRR(flows!$C$380:$C$385,flows!$B$380:$B$385),"NUM") -> 2.9429553 | E75: =IF(ISNUMBER(D75),IFERROR(XNPV(D75,flows!$C$380:$C$385,flows!$B$380:$B$385),"ERR"),"") -> -1.3145041e-13
A76: fuzz/041 | B76: 7 | C76: 2 | D76: =IFERROR(XIRR(flows!$C$386:$C$392,flows!$B$386:$B$392),"NUM") -> NUM | E76: =IF(ISNUMBER(D76),IFERROR(XNPV(D76,flows!$C$386:$C$392,flows!$B$386:$B$392),"ERR"),"")
A77: fuzz/042 | B77: 7 | C77: 4 | D77: =IFERROR(XIRR(flows!$C$393:$C$399,flows!$B$393:$B$399),"NUM") -> 0.3245217 | E77: =IF(ISNUMBER(D77),IFERROR(XNPV(D77,flows!$C$393:$C$399,flows!$B$393:$B$399),"ERR"),"") -> 6.8212103e-13
A78: fuzz/043 | B78: 3 | C78: 1 | D78: =IFERROR(XIRR(flows!$C$400:$C$402,flows!$B$400:$B$402),"NUM") -> -0.55696118 | E78: =IF(ISNUMBER(D78),IFERROR(XNPV(D78,flows!$C$400:$C$402,flows!$B$400:$B$402),"ERR"),"") -> 0
A79: fuzz/045 | B79: 5 | C79: 2 | D79: =IFERROR(XIRR(flows!$C$403:$C$407,flows!$B$403:$B$407),"NUM") -> NUM | E79: =IF(ISNUMBER(D79),IFERROR(XNPV(D79,flows!$C$403:$C$407,flows!$B$403:$B$407),"ERR"),"")
A80: fuzz/047 | B80: 8 | C80: 1 | D80: =IFERROR(XIRR(flows!$C$408:$C$415,flows!$B$408:$B$415),"NUM") -> -0.81417783 | E80: =IF(ISNUMBER(D80),IFERROR(XNPV(D80,flows!$C$408:$C$415,flows!$B$408:$B$415),"ERR"),"") -> 3.7252903e-09
A81: fuzz/048 | B81: 5 | C81: 2 | D81: =IFERROR(XIRR(flows!$C$416:$C$420,flows!$B$416:$B$420),"NUM") -> NUM | E81: =IF(ISNUMBER(D81),IFERROR(XNPV(D81,flows!$C$416:$C$420,flows!$B$416:$B$420),"ERR"),"")
A82: fuzz/049 | B82: 7 | C82: 2 | D82: =IFERROR(XIRR(flows!$C$421:$C$427,flows!$B$421:$B$427),"NUM") -> NUM | E82: =IF(ISNUMBER(D82),IFERROR(XNPV(D82,flows!$C$421:$C$427,flows!$B$421:$B$427),"ERR"),"")
A83: fuzz/050 | B83: 7 | C83: 1 | D83: =IFERROR(XIRR(flows!$C$428:$C$434,flows!$B$428:$B$434),"NUM") -> -0.18547889 | E83: =IF(ISNUMBER(D83),IFERROR(XNPV(D83,flows!$C$428:$C$434,flows!$B$428:$B$434),"ERR"),"") -> -1.8189894e-12
A84: fuzz/051 | B84: 7 | C84: 3 | D84: =IFERROR(XIRR(flows!$C$435:$C$441,flows!$B$435:$B$441),"NUM") -> -0.54415599 | E84: =IF(ISNUMBER(D84),IFERROR(XNPV(D84,flows!$C$435:$C$441,flows!$B$435:$B$441),"ERR"),"") -> 5.4569682e-12
A85: fuzz/052 | B85: 8 | C85: 4 | D85: =IFERROR(XIRR(flows!$C$442:$C$449,flows!$B$442:$B$449),"NUM") -> NUM | E85: =IF(ISNUMBER(D85),IFERROR(XNPV(D85,flows!$C$442:$C$449,flows!$B$442:$B$449),"ERR"),"")
A86: fuzz/053 | B86: 8 | C86: 3 | D86: =IFERROR(XIRR(flows!$C$450:$C$457,flows!$B$450:$B$457),"NUM") -> -0.82529145 | E86: =IF(ISNUMBER(D86),IFERROR(XNPV(D86,flows!$C$450:$C$457,flows!$B$450:$B$457),"ERR"),"") -> -4.6566129e-10
A87: fuzz/054 | B87: 8 | C87: 2 | D87: =IFERROR(XIRR(flows!$C$458:$C$465,flows!$B$458:$B$465),"NUM") -> NUM | E87: =IF(ISNUMBER(D87),IFERROR(XNPV(D87,flows!$C$458:$C$465,flows!$B$458:$B$465),"ERR"),"")
A88: fuzz/056 | B88: 3 | C88: 2 | D88: =IFERROR(XIRR(flows!$C$466:$C$468,flows!$B$466:$B$468),"NUM") -> NUM | E88: =IF(ISNUMBER(D88),IFERROR(XNPV(D88,flows!$C$466:$C$468,flows!$B$466:$B$468),"ERR"),"")
A89: fuzz/057 | B89: 6 | C89: 4 | D89: =IFERROR(XIRR(flows!$C$469:$C$474,flows!$B$469:$B$474),"NUM") -> NUM | E89: =IF(ISNUMBER(D89),IFERROR(XNPV(D89,flows!$C$469:$C$474,flows!$B$469:$B$474),"ERR"),"")
A90: fuzz/058 | B90: 7 | C90: 3 | D90: =IFERROR(XIRR(flows!$C$475:$C$481,flows!$B$475:$B$481),"NUM") -> 0.28429367 | E90: =IF(ISNUMBER(D90),IFERROR(XNPV(D90,flows!$C$475:$C$481,flows!$B$475:$B$481),"ERR"),"") -> 4.5474735e-13
A92: xirr uses the engine default guess (10%). NUM = the engine reported a numeric error (no solution found).
